AUTHORS.rst
CHANGES.rst
LICENSE
MANIFEST.in
README.rst
VERSION
requirements-dev.txt
requirements.txt
setup.cfg
setup.py
molo/__init__.py
molo.yourtips.egg-info/PKG-INFO
molo.yourtips.egg-info/SOURCES.txt
molo.yourtips.egg-info/dependency_links.txt
molo.yourtips.egg-info/namespace_packages.txt
molo.yourtips.egg-info/not-zip-safe
molo.yourtips.egg-info/requires.txt
molo.yourtips.egg-info/top_level.txt
molo/yourtips/__init__.py
molo/yourtips/admin.py
molo/yourtips/forms.py
molo/yourtips/models.py
molo/yourtips/urls.py
molo/yourtips/views.py
molo/yourtips/wagtail_hooks.py
molo/yourtips/migrations/0001_initial.py
molo/yourtips/migrations/0002_create_index_tip_page.py
molo/yourtips/migrations/0003_add_homepage_action_copy.py
molo/yourtips/migrations/0004_yourtip_language_translated_pages.py
molo/yourtips/migrations/__init__.py
molo/yourtips/templates/__init__.py
molo/yourtips/templates/admin/__init__.py
molo/yourtips/templates/admin/yourtips/__init__.py
molo/yourtips/templates/admin/yourtips/model_admin_template.html
molo/yourtips/templates/admin/yourtips/model_admin_your_tip_template.html
molo/yourtips/templates/admin/yourtips/yourtips_entry_date_range_filter.html
molo/yourtips/templates/admin/yourtips/yourtips_tip_date_range_filter.html
molo/yourtips/templates/likes/inclusion_tags/likes.html
molo/yourtips/templates/patterns/basics/forms/form.html
molo/yourtips/templates/patterns/basics/page/yourtips-body.html
molo/yourtips/templates/patterns/basics/promoted-tips/promoted-tips-heading.html
molo/yourtips/templates/patterns/basics/promoted-tips/promoted-tips-list.html
molo/yourtips/templates/patterns/basics/promoted-tips/social-media.html
molo/yourtips/templates/patterns/basics/promoted-tips/yourtips-article-tag.html
molo/yourtips/templates/patterns/basics/promoted-tips/yourtips-on-submission-form.html
molo/yourtips/templates/yourtips/popular_tips.html
molo/yourtips/templates/yourtips/recent_tips.html
molo/yourtips/templates/yourtips/thank_you.html
molo/yourtips/templates/yourtips/your_tip.html
molo/yourtips/templates/yourtips/your_tips_breadcrumbs.html
molo/yourtips/templates/yourtips/your_tips_create_tip_on_homepage.html
molo/yourtips/templates/yourtips/your_tips_entry.html
