Metadata-Version: 1.1
Name: molo.yourtips
Version: 7.0.0
Summary: This feature enables youth to share short tips with one another
Home-page: https://github.com/praekeltfoundation/molo.yourtips
Author: Praekelt Foundation
Author-email: dev@praekelt.com
License: BSD
Keywords: praekelt,mobi,web,django
Platform: UNKNOWN
Classifier: Programming Language :: Python
Classifier: Framework :: Django
Classifier: Topic :: Internet :: WWW/HTTP
Classifier: Topic :: Internet :: WWW/HTTP :: WSGI :: Application
